clock_tracking/__init__.py
clock_tracking/__main__.py
clock_tracking/clock.py
clock_tracking/colors.py
clock_tracking/config.py
clock_tracking/datetimeutils.py
clock_tracking/filters.py
clock_tracking/logger.py
clock_tracking/options.py
clock_tracking/report.py
clock_tracking/task.py
clock_tracking_tests/__init__.py
clock_tracking_tests/test_filters.py
clock_tracking_tests/test_logger.py
clock_tracking_tests/test_options.py
clock_tracking_tests/test_task.py
clock_tracking-0.0.7.dist-info/LICENSE
clock_tracking-0.0.7.dist-info/METADATA
clock_tracking-0.0.7.dist-info/WHEEL
clock_tracking-0.0.7.dist-info/top_level.txt
clock_tracking-0.0.7.dist-info/RECORD
