Metadata-Version: 2.1
Name: clock-tracking
Version: 0.0.7
Summary: Time tracking management from python / command line
Home-page: https://github.com/computoms/clock
Author: Computoms
Author-email: thomas.computoms@gmail.com
License: UNKNOWN
Platform: UNKNOWN
Classifier: Programming Language :: Python :: 3
Classifier: Operating System :: OS Independent
Requires-Python: >=2.8
License-File: LICENSE
